yellowdog_ray/__init__.py
yellowdog_ray/py.typed
yellowdog_ray/raydog/__init__.py
yellowdog_ray/raydog/__init__.pyi
yellowdog_ray/raydog/autoscaler.py
yellowdog_ray/raydog/autoscaler.pyi
yellowdog_ray/raydog/builder.py
yellowdog_ray/raydog/builder.pyi
yellowdog_ray/utils/__init__.py
yellowdog_ray/utils/__init__.pyi
yellowdog_ray/utils/ray_ssh_tunnels.py
yellowdog_ray/utils/ray_ssh_tunnels.pyi
yellowdog_ray/utils/utils.py
yellowdog_ray/utils/utils.pyi
yellowdog_ray-0.1.5.dist-info/licenses/LICENSE
yellowdog_ray-0.1.5.dist-info/METADATA
yellowdog_ray-0.1.5.dist-info/WHEEL
yellowdog_ray-0.1.5.dist-info/top_level.txt
yellowdog_ray-0.1.5.dist-info/RECORD
