Metadata-Version: 2.4
Name: yellowdog-ray
Version: 0.1.5
Summary: RayDog: YellowDog Integration with Ray.
Author-email: YellowDog Limited <support@yellowdog.co>
License-Expression: Apache-2.0
Project-URL: Homepage, https://github.com/yellowdog/raydog
Project-URL: Source, https://github.com/yellowdog/raydog
Classifier: Programming Language :: Python :: 3.10
Classifier: Programming Language :: Python :: 3.11
Classifier: Programming Language :: Python :: 3.12
Classifier: Operating System :: OS Independent
Classifier: Development Status :: 4 - Beta
Requires-Python: <3.13,>=3.10
License-File: LICENSE
Requires-Dist: paramiko<=3.5.1
Requires-Dist: python-dotenv
Requires-Dist: ray[client]
Requires-Dist: redis
Requires-Dist: requests
Requires-Dist: sshtunnel
Requires-Dist: yellowdog-sdk>=11.2.0
Dynamic: license-file
